Workbook

Sheet Customers
A1: CustomerID | B1: FirstName | C1: LastName | D1: Gender | E1: BirthDate | F1: City | G1: JoinDate
A2: C001 | B2: Michael | C2: Davis | D2: M | E2: 35319 | F2: Osborneport | G2: 44829
A3: C002 | B3: Michael | C3: Miller | D3: M | E3: 21780 | F3: New Gabrielleport | G3: 44138
A4: C003 | B4: Carol | C4: Hays | D4: F | E4: 38461 | F4: Port Allen | G4: 45334
A5: C004 | B5: Joseph | C5: Ward | D5: M | E5: 33771 | F5: East Edgarborough | G5: 45544
A6: C005 | B6: Jamie | C6: Salinas | D6: M | E6: 33773 | F6: Port Kimberly | G6: 44616
A7: C006 | B7: Danny | C7: Moore | D7: M | E7: 31688 | F7: Costaberg | G7: 44751
A8: C007 | B8: Erin | C8: Walker | D8: M | E8: 31058 | F8: West Jasmine | G8: 44482
A9: C008 | B9: Isaiah | C9: Williams | D9: M | E9: 22233 | F9: New Michaelland | G9: 45720
A10: C009 | B10: Richard | C10: Pacheco | D10: F | E10: 38214 | F10: West Lisaville | G10: 45764
A11: C010 | B11: Catherine | C11: Rice | D11: M | E11: 28106 | F11: West Carol | G11: 45861
A12: C011 | B12: Haley | C12: Williams | D12: M | E12: 35492 | F12: Leburgh | G12: 45058
A13: C012 | B13: Dale | C13: Perry | D13: M | E13: 32850 | F13: Lake Dawn | G13: 44393
... A201: C200 | B201: Ronald | C201: Haley | D201: M | E201: 37249 | F201: Jenniferbury | G201: 45832

Sheet Products
A1: ProductID | B1: ProductName | C1: Category | D1: SubCategory | E1: UnitPrice | F1: CostPrice
A2: P001 | B2: Like Camera | C2: Electronics | D2: Camera | E2: 1673.69 | F2: 1323.38
A3: P002 | B3: Audience Television | C3: Electronics | D3: Television | E3: 818.76 | F3: 527.62
A4: P003 | B4: Here Footwear | C4: Fashion | D4: Footwear | E4: 337.63 | F4: 169.03
A5: P004 | B5: Four Accessories | C5: Fashion | D5: Accessories | E5: 1853.77 | F5: 1363.52
A6: P005 | B6: Knowledge Bags | C6: Fashion | D6: Bags | E6: 1396.22 | F6: 1004.09
A7: P006 | B7: Company Fruits | C7: Groceries | D7: Fruits | E7: 318.05 | F7: 187.34
A8: P007 | B8: Understand Camera | C8: Electronics | D8: Camera | E8: 1474.12 | F8: 764.02
A9: P008 | B9: Recognize Footwear | C9: Fashion | D9: Footwear | E9: 109.78 | F9: 70.59
A10: P009 | B10: Us Snacks | C10: Groceries | D10: Snacks | E10: 123.19 | F10: 80.36
A11: P010 | B11: Step Smartphone | C11: Electronics | D11: Smartphone | E11: 1194.12 | F11: 838.95
A12: P011 | B12: Either Headphones | C12: Electronics | D12: Headphones | E12: 248.57 | F12: 190.67
A13: P012 | B13: Above Camera | C13: Electronics | D13: Camera | E13: 1193.09 | F13: 818.24
... A51: P050 | B51: Maybe Footwear | C51: Fashion | D51: Footwear | E51: 1044.64 | F51: 775.07

Sheet Stores
A1: StoreID | B1: StoreName | C1: City | D1: Region
A2: S001 | B2: MegaMart Jimenezborough | C2: Jimenezborough | D2: South
A3: S002 | B3: MegaMart Peckmouth | C3: Peckmouth | D3: East
A4: S003 | B4: MegaMart New Michele | C4: New Michele | D4: West
A5: S004 | B5: MegaMart Brianahaven | C5: Brianahaven | D5: North
A6: S005 | B6: MegaMart Johnmouth | C6: Johnmouth | D6: East

Sheet Transactions
A1: TransactionID | B1: Date | C1: CustomerID | D1: ProductID | E1: StoreID | F1: Quantity | G1: Discount | H1: PaymentMethod | I1: Total Sales
A2: T00001 | B2: 45461 | C2: C160 | D2: P014 | E2: S003 | F2: 1 | G2: 0.1 | H2: Bank Transfer | I2: =IF(OR(D2="", F2=""), "", F2 * VLOOKUP(D2, Products!A:E, 5, FALSE) * (1 - G2)) -> 1208.475
A3: T00002 | B3: 45232 | C3: C171 | D3: P030 | E3: S004 | F3: 3 | G3: 0.15 | H3: Bank Transfer | I3: =IF(OR(D3="", F3=""), "", F3 * VLOOKUP(D3, Products!A:E, 5, FALSE) * (1 - G3)) -> 74.562
A4: T00003 | B4: 45379 | C4: C142 | D4: P002 | E4: S002 | F4: 2 | G4: 0.15 | H4: Mobile Money | I4: =IF(OR(D4="", F4=""), "", F4 * VLOOKUP(D4, Products!A:E, 5, FALSE) * (1 - G4)) -> 1391.892
A5: T00004 | B5: 45458 | C5: C174 | D5: P050 | E5: S002 | F5: 5 | G5: 0.1 | H5: Mobile Money | I5: =IF(OR(D5="", F5=""), "", F5 * VLOOKUP(D5, Products!A:E, 5, FALSE) * (1 - G5)) -> 4700.88
A6: T00005 | B6: 45533 | C6: C141 | D6: P036 | E6: S001 | F6: 3 | G6: 0.1 | H6: Credit Card | I6: =IF(OR(D6="", F6=""), "", F6 * VLOOKUP(D6, Products!A:E, 5, FALSE) * (1 - G6)) -> 4053.942
A7: T00006 | B7: 45744 | C7: C111 | D7: P036 | E7: S005 | F7: 5 | G7: 0.1 | H7: Mobile Money | I7: =IF(OR(D7="", F7=""), "", F7 * VLOOKUP(D7, Products!A:E, 5, FALSE) * (1 - G7)) -> 6756.57
A8: T00007 | B8: 45605 | C8: C114 | D8: P009 | E8: S004 | F8: 2 | G8: 0.15 | H8: Credit Card | I8: =IF(OR(D8="", F8=""), "", F8 * VLOOKUP(D8, Products!A:E, 5, FALSE) * (1 - G8)) -> 209.423
A9: T00008 | B9: 45440 | C9: C169 | D9: P005 | E9: S001 | F9: 3 | G9: 0.1 | H9: Cash | I9: =IF(OR(D9="", F9=""), "", F9 * VLOOKUP(D9, Products!A:E, 5, FALSE) * (1 - G9)) -> 3769.794
A10: T00009 | B10: 45539 | C10: C193 | D10: P035 | E10: S002 | F10: 3 | G10: 0.05 | H10: Credit Card | I10: =IF(OR(D10="", F10=""), "", F10 * VLOOKUP(D10, Products!A:E, 5, FALSE) * (1 - G10)) -> 4452.9255
A11: T00010 | B11: 45459 | C11: C038 | D11: P045 | E11: S001 | F11: 1 | G11: 0.05 | H11: Mobile Money | I11: =IF(OR(D11="", F11=""), "", F11 * VLOOKUP(D11, Products!A:E, 5, FALSE) * (1 - G11)) -> 1785.126
A12: T00011 | B12: 45725 | C12: C157 | D12: P022 | E12: S001 | F12: 4 | G12: 0.15 | H12: Credit Card | I12: =IF(OR(D12="", F12=""), "", F12 * VLOOKUP(D12, Products!A:E, 5, FALSE) * (1 - G12)) -> 86.938
A13: T00012 | B13: 45449 | C13: C184 | D13: P042 | E13: S004 | F13: 4 | G13: 0.15 | H13: Credit Card | I13: =IF(OR(D13="", F13=""), "", F13 * VLOOKUP(D13, Products!A:E, 5, FALSE) * (1 - G13)) -> 1542.308
... A5001: T05000 | B5001: 45489 | C5001: C053 | D5001: P034 | E5001: S004 | F5001: 5 | G5001: 0.15 | H5001: Cash | I5001: =IF(OR(D5001="", F5001=""), "", F5001 * VLOOKUP(D5001, Products!A:E, 5, FALSE) * (1 - G5001)) -> 1819.2125

Sheet SUMMARY
A1: DAILY SALES SUMMARY
A2: Target Date | B2: Daily Total
A3: 45461 | B3: =SUMIF(Transactions!B:B, A3, Transactions!I:I) -> 13058.176
A5: WEEKLY SALES SUMMARY
A6: Start Date | B6: End Date | C6: Weekly Total
A7: 45459 | B7: 45465 | C7: =SUMIFS(Transactions!I:I, Transactions!B:B, ">="&A7, Transactions!B:B, "<="&B7) -> 150499.53
A9: MONTHLY SALES SUMMARY
A10: Start Date | B10: End Date | C10: Monthly Total
A11: 45444 | B11: 45473 | C11: =SUMIFS(Transactions!I:I, Transactions!B:B, ">="&A11, Transactions!B:B, "<="&B11) -> 634753.77
A12: TOTAL REVENUE- OUTPUT
A13: =SUM(Transactions!I:I) -> 14301903
